MANIFEST.in
README.rst
generate.py
setup.py
fbsd_gpio/__init__.py
fbsd_gpio/constant.py
fbsd_gpio.egg-info/PKG-INFO
fbsd_gpio.egg-info/SOURCES.txt
fbsd_gpio.egg-info/dependency_links.txt
fbsd_gpio.egg-info/requires.txt
fbsd_gpio.egg-info/top_level.txt