Metadata-Version: 1.1
Name: fbsd-gpio
Version: 0.5.0
Summary: cffi-based Python bindings for FreeBSD GPIO
Home-page: https://github.com/evadot/fbsd_gpio_py
Author: Emmanuel Vadot
Author-email: manu@bidouilliste.com
License: BSD
Keywords: FreeBSD GPIO
Platform: UNKNOWN
Classifier: Development Status :: 5 - Production/Stable
Classifier: Intended Audience :: Developers
Classifier: License :: OSI Approved :: BSD License
Classifier: Operating System :: POSIX :: BSD :: FreeBSD
Classifier: Programming Language :: Python
Classifier: Programming Language :: Python :: 2.7
Classifier: Programming Language :: Python :: 3
Classifier: Programming Language :: Python :: 3.3
Classifier: Programming Language :: Python :: 3.4
Classifier: Programming Language :: Python :: Implementation :: CPython
